<?xml version="1.0" encoding="UTF-8"?>

<wicast>

	<client>
		<source id="source-id" name="source-name" address="channel.wicast.net" ip="224.1.1.1" port="1234" />
		<source id="" name="" ip="" port="" />
	</client>

	<server>
		<channel id="1" name="localhost" ip="127.0.0.1" port="1234">
			<data />
		</channel>
		<channel id="2" name="localhost" ip="127.0.0.2" port="1234">
			<data />
		</channel>
	</server>

	<relay>
		<source id="" name="" ip="127.0.0.1" port="">
			<destination id="" name="" ip="127.0.0.2" port="" />
		</source>
		<source id="" name="" ip="" port="">
			<destination id="" name="" ip="" port="" />
		</source>
	</relay>

</wicast>
